project/m2/rtl/interface.sv
// ============================================================================
// interface.sv  —  Conv2d Co-processor Chiplet Interface Module
// ECE 410/510 — Anemia Detection Accelerator, Milestone 2
//

//
// Implements the M1-selected interface:
//   Data plane  — AXI4-Stream slave, 512-bit data width
//                 (AMBA AXI4-Stream Protocol Spec IHI0051, TVALID/TREADY contract)
//   Control plane — AXI4-Lite slave, 32-bit data, 4-bit address
//                 (AMBA AXI4-Lite Spec IHI0022, handshake on every channel)
//
// ── Register map (AXI4-Lite, 4-bit address space) ──────────────────────────
//   Addr  Name      Access  Bits     Description
//   0x00  CTRL      W       [0]      start    — write 1 to pulse core_start (auto-clears)
//                           [1]      sw_rst   — software reset request (auto-clears)
//   0x04  STATUS    R       [0]      done     — latched from core_done; clears on read
//                           [1]      busy     — asserted when core is not idle
//   0x08  TILE_LEN  RW      [7:0]   num_elem — number of MAC operations per tile
//   0x0C  RESULT    R       [31:0]  q1616    — Q16.16 output pixel (latched on done)
//
// ── AXI4-Stream transaction format ──────────────────────────────────────────
//   Each beat carries 512 bits of packed data (16 × 32-bit Q16.16 values).
//   TDATA[31:0] of the first beat is captured into stream_buf for inspection.
//   TLAST marks the final beat of a tile packet.
//   TREADY is held high; the interface always accepts incoming beats.
//
// Ports:
//   clk              in    1    System clock (target 1 GHz)
//   rst_n            in    1    Synchronous active-low reset
//   s_axil_awaddr    in    4    AXI4-Lite write address
//   s_axil_awvalid   in    1    Write address valid
//   s_axil_awready   out   1    Write address ready
//   s_axil_wdata     in   32    Write data
//   s_axil_wstrb     in    4    Write byte strobes (unused; all bytes written)
//   s_axil_wvalid    in    1    Write data valid
//   s_axil_wready    out   1    Write data ready
//   s_axil_bresp     out   2    Write response (2'b00 = OKAY)
//   s_axil_bvalid    out   1    Write response valid
//   s_axil_bready    in    1    Write response ready
//   s_axil_araddr    in    4    AXI4-Lite read address
//   s_axil_arvalid   in    1    Read address valid
//   s_axil_arready   out   1    Read address ready
//   s_axil_rdata     out  32    Read data
//   s_axil_rresp     out   2    Read response (2'b00 = OKAY)
//   s_axil_rvalid    out   1    Read data valid
//   s_axil_rready    in    1    Read data ready
//   s_axis_tdata     in  512    AXI4-Stream packed data beat
//   s_axis_tvalid    in    1    Stream data valid
//   s_axis_tready    out   1    Stream ready (always 1)
//   s_axis_tlast     in    1    Last beat of packet
//   core_start       out   1    Forwarded start pulse to compute_core
//   core_tile_len    out   8    Tile length forwarded to compute_core
//   core_result      in   32    Result from compute_core
//   core_done        in    1    Done pulse from compute_core
//   core_ready       in    1    Idle flag from compute_core
//
// Clock domain : single (clk)
// Reset        : synchronous, active-low (rst_n = 0 clears all registers)
// ============================================================================

module conv_interface #(
    parameter int AXIS_DATA_W = 512,
    parameter int AXIL_ADDR_W = 4,
    parameter int AXIL_DATA_W = 32
) (
    input  logic clk,
    input  logic rst_n,

    // ── AXI4-Lite write address channel ─────────────────────────────────
    input  logic [AXIL_ADDR_W-1:0] s_axil_awaddr,
    input  logic                    s_axil_awvalid,
    output logic                    s_axil_awready,

    // ── AXI4-Lite write data channel ────────────────────────────────────
    input  logic [AXIL_DATA_W-1:0] s_axil_wdata,
    input  logic [3:0]              s_axil_wstrb,
    input  logic                    s_axil_wvalid,
    output logic                    s_axil_wready,

    // ── AXI4-Lite write response channel ────────────────────────────────
    output logic [1:0]              s_axil_bresp,
    output logic                    s_axil_bvalid,
    input  logic                    s_axil_bready,

    // ── AXI4-Lite read address channel ──────────────────────────────────
    input  logic [AXIL_ADDR_W-1:0] s_axil_araddr,
    input  logic                    s_axil_arvalid,
    output logic                    s_axil_arready,

    // ── AXI4-Lite read data channel ─────────────────────────────────────
    output logic [AXIL_DATA_W-1:0] s_axil_rdata,
    output logic [1:0]              s_axil_rresp,
    output logic                    s_axil_rvalid,
    input  logic                    s_axil_rready,

    // ── AXI4-Stream slave (data plane) ──────────────────────────────────
    input  logic [AXIS_DATA_W-1:0] s_axis_tdata,
    input  logic                    s_axis_tvalid,
    output logic                    s_axis_tready,
    input  logic                    s_axis_tlast,

    // ── Compute core interface ───────────────────────────────────────────
    output logic        core_start,
    output logic [7:0]  core_tile_len,
    input  logic [31:0] core_result,
    input  logic        core_done,
    input  logic        core_ready
);

    // ── internal registers ────────────────────────────────────────────────
    logic        reg_start;      // auto-clears after one cycle
    logic        reg_done;       // latched from core_done, clears on STATUS read
    logic [7:0]  reg_tile_len;   // tile length register
    logic [31:0] reg_result;     // output pixel latch
    logic [31:0] stream_buf;     // first 32 bits of last stream beat

    // ── AXI4-Lite write path state ────────────────────────────────────────
    logic                    aw_latch;  // write address pending
    logic [AXIL_ADDR_W-1:0] aw_addr;
    logic                    w_latch;   // write data pending
    logic [AXIL_DATA_W-1:0] w_data;
    logic                    b_pend;    // write response pending

    // ── AXI4-Lite read path state ─────────────────────────────────────────
    logic r_pend;  // read response pending

    // ── combinational output assignments ──────────────────────────────────
    assign s_axil_awready = !aw_latch && !b_pend;
    assign s_axil_wready  = !w_latch  && !b_pend;
    assign s_axil_bresp   = 2'b00;
    assign s_axil_bvalid  = b_pend;

    assign s_axil_arready = !r_pend;
    assign s_axil_rresp   = 2'b00;
    assign s_axil_rvalid  = r_pend;

    assign s_axis_tready  = 1'b1;   // always ready; no backpressure

    // ── write mux: prefer latched values; fall back to current-cycle bus ──
    // Used inside always_ff to avoid unsupported ternary-bit-select syntax.
    logic [AXIL_ADDR_W-1:0] wr_addr;
    logic [AXIL_DATA_W-1:0] wr_data;
    assign wr_addr = aw_latch ? aw_addr    : s_axil_awaddr;
    assign wr_data = w_latch  ? w_data     : s_axil_wdata;

    assign core_start     = reg_start;
    assign core_tile_len  = reg_tile_len;

    // ── registered logic ──────────────────────────────────────────────────
    always_ff @(posedge clk) begin
        if (!rst_n) begin
            aw_latch     <= 1'b0;  aw_addr  <= '0;
            w_latch      <= 1'b0;  w_data   <= '0;
            b_pend       <= 1'b0;
            r_pend       <= 1'b0;
            s_axil_rdata <= '0;
            reg_start    <= 1'b0;
            reg_done     <= 1'b0;
            reg_tile_len <= 8'd0;
            reg_result   <= 32'd0;
            stream_buf   <= 32'd0;
        end else begin

            // ── auto-clear start pulse ────────────────────────────────
            reg_start <= 1'b0;

            // ── latch core result on done ─────────────────────────────
            if (core_done) begin
                reg_done   <= 1'b1;
                reg_result <= core_result;
            end

            // ── AXI4-Stream beat capture ──────────────────────────────
            // TVALID/TREADY contract: transfer on any cycle both are high.
            if (s_axis_tvalid) begin
                stream_buf <= s_axis_tdata[31:0];
            end

            // ── AXI4-Lite write address latch ─────────────────────────
            if (s_axil_awvalid && s_axil_awready) begin
                aw_latch <= 1'b1;
                aw_addr  <= s_axil_awaddr;
            end

            // ── AXI4-Lite write data latch ────────────────────────────
            if (s_axil_wvalid && s_axil_wready) begin
                w_latch <= 1'b1;
                w_data  <= s_axil_wdata;
            end

            // ── perform write when both AW and W are present ──────────
            // Either from the latch registers (separate arrival) or
            // directly from the bus (simultaneous arrival, common in AXI4-Lite).
            if ((aw_latch || (s_axil_awvalid && s_axil_awready)) &&
                (w_latch  || (s_axil_wvalid  && s_axil_wready ))) begin

                // wr_addr/wr_data: combinational mux selecting latched or
                // current-cycle values (handles separate or simultaneous AW/W)
                case (wr_addr[3:2])
                    2'b00: begin          // 0x00 CTRL
                        if (wr_data[0]) reg_start <= 1'b1;
                    end
                    2'b10: begin          // 0x08 TILE_LEN
                        reg_tile_len <= wr_data[7:0];
                    end
                    default: ;            // 0x04 STATUS, 0x0C RESULT are read-only
                endcase

                aw_latch <= 1'b0;
                w_latch  <= 1'b0;
                b_pend   <= 1'b1;
            end

            // ── clear write response after BREADY ─────────────────────
            if (b_pend && s_axil_bready) begin
                b_pend <= 1'b0;
            end

            // ── AXI4-Lite read: accept address, register response ─────
            if (s_axil_arvalid && s_axil_arready) begin
                r_pend <= 1'b1;
                case (s_axil_araddr[3:2])
                    2'b00: s_axil_rdata <= {30'd0, 1'b0, reg_start};
                    2'b01: begin
                        s_axil_rdata <= {30'd0, !core_ready, reg_done};
                        reg_done     <= 1'b0;  // clear done flag on STATUS read
                    end
                    2'b10: s_axil_rdata <= {24'd0, reg_tile_len};
                    2'b11: s_axil_rdata <= reg_result;
                    default: s_axil_rdata <= 32'd0;
                endcase
            end

            // ── clear read response after RREADY ──────────────────────
            if (r_pend && s_axil_rready) begin
                r_pend <= 1'b0;
            end

        end
    end

endmodule

project/m2/tb/tb_interface.sv
// ============================================================================
// tb_interface.sv
// ECE 410/510 — Testbench: conv_interface
//
// Exercises all four required transaction types and prints PASS / FAIL.
//
// Test 1 — AXI4-Lite write (complete transaction):
//   Write TILE_LEN = 9 to register 0x08.
//   AW + W channels presented simultaneously; B response accepted.
//   Pass condition: BRESP = 2'b00 (OKAY).
//
// Test 2 — AXI4-Lite read (complete transaction):
//   Read TILE_LEN back from register 0x08.
//   AR channel presented; R channel data captured.
//   Pass condition: RDATA[7:0] = 8'd9, RRESP = 2'b00.
//
// Test 3 — AXI4-Stream write beat:
//   Send one TDATA beat (512-bit, non-trivial pattern) with TLAST.
//   Pass condition: TREADY = 1 during the beat (transfer accepted).
//
// Test 4 — CTRL start pulse:
//   Write 0x1 to CTRL register (0x00); DUT must drive core_start = 1
//   for exactly one clock cycle.
//   Pass condition: core_start sampled high immediately after write posedge.
//
// Simulator: Icarus Verilog
//   iverilog -g2012 -o sim_if.out interface.sv tb_interface.sv && vvp sim_if.out
// ============================================================================

`timescale 1ns/1ps

module tb_interface;

    // ── DUT port signals ──────────────────────────────────────────────────
    logic        clk, rst_n;

    // AXI4-Lite
    logic [3:0]  awaddr;  logic        awvalid; logic awready;
    logic [31:0] wdata;   logic [3:0]  wstrb;   logic wvalid;  logic wready;
    logic [1:0]  bresp;   logic        bvalid;  logic bready;
    logic [3:0]  araddr;  logic        arvalid; logic arready;
    logic [31:0] rdata;   logic [1:0]  rresp;   logic rvalid;  logic rready;

    // AXI4-Stream
    logic [511:0] tdata;
    logic          tvalid, tready, tlast;

    // Core stub signals
    logic        core_start;
    logic [7:0]  core_tile_len;
    logic [31:0] core_result;
    logic        core_done, core_ready;

    // ── DUT instantiation ─────────────────────────────────────────────────
    conv_interface dut (
        .clk            (clk),
        .rst_n          (rst_n),
        // AXI4-Lite write address
        .s_axil_awaddr  (awaddr),  .s_axil_awvalid(awvalid), .s_axil_awready(awready),
        // AXI4-Lite write data
        .s_axil_wdata   (wdata),   .s_axil_wstrb  (wstrb),
        .s_axil_wvalid  (wvalid),  .s_axil_wready (wready),
        // AXI4-Lite write response
        .s_axil_bresp   (bresp),   .s_axil_bvalid (bvalid),  .s_axil_bready(bready),
        // AXI4-Lite read address
        .s_axil_araddr  (araddr),  .s_axil_arvalid(arvalid), .s_axil_arready(arready),
        // AXI4-Lite read data
        .s_axil_rdata   (rdata),   .s_axil_rresp  (rresp),
        .s_axil_rvalid  (rvalid),  .s_axil_rready (rready),
        // AXI4-Stream
        .s_axis_tdata   (tdata),   .s_axis_tvalid (tvalid),
        .s_axis_tready  (tready),  .s_axis_tlast  (tlast),
        // Core interface
        .core_start     (core_start),  .core_tile_len(core_tile_len),
        .core_result    (core_result), .core_done    (core_done),
        .core_ready     (core_ready)
    );

    // ── 1 GHz clock ───────────────────────────────────────────────────────
    initial clk = 0;
    always  #0.5 clk = ~clk;

    // ── VCD dump ──────────────────────────────────────────────────────────
    initial begin
        $dumpfile("sim/waveform.vcd");
        $dumpvars(1, tb_interface);
    end

    // ── core stubs: no compute_core attached for this testbench ───────────
    assign core_done   = 1'b0;
    assign core_ready  = 1'b1;
    assign core_result = 32'd0;

    // ── counters and shared variables ─────────────────────────────────────
    integer      pass_count, fail_count;
    logic [31:0] read_val;
    logic        got_start;

    // ── AXI4-Lite write task ──────────────────────────────────────────────
    // Presents AW and W simultaneously (standard AXI4-Lite master practice).
    // Waits for AWREADY & WREADY, then waits for BVALID and accepts BRESP.
    task axil_write;
        input [3:0]  addr;
        input [31:0] data;
        // present address + data
        @(posedge clk); #0.1;
        awaddr  = addr;  awvalid = 1'b1;
        wdata   = data;  wvalid  = 1'b1;  wstrb = 4'hF;
        // spin until both channels are accepted (ready signals go high)
        while (!(awready && wready)) @(posedge clk);
        // posedge where DUT samples the handshake
        @(posedge clk); #0.1;
        awvalid = 1'b0;  wvalid = 1'b0;
        // wait for write response
        while (!bvalid) @(posedge clk);
        #0.1; bready = 1'b1;
        @(posedge clk); #0.1;
        bready = 1'b0;
    endtask

    // ── AXI4-Lite read task ───────────────────────────────────────────────
    // Presents AR, waits for ARREADY, then waits for RVALID and captures data.
    task axil_read;
        input  [3:0]  addr;
        output [31:0] rd_data;
        @(posedge clk); #0.1;
        araddr  = addr;  arvalid = 1'b1;
        while (!arready) @(posedge clk);
        @(posedge clk); #0.1;
        arvalid = 1'b0;
        while (!rvalid) @(posedge clk);
        rd_data = rdata;
        #0.1; rready = 1'b1;
        @(posedge clk); #0.1;
        rready = 1'b0;
    endtask

    // ── main stimulus ─────────────────────────────────────────────────────
    initial begin : stim

        // initialise all inputs
        pass_count = 0;  fail_count = 0;
        rst_n   = 1'b0;
        awaddr  = 4'h0;   awvalid = 1'b0;
        wdata   = 32'd0;  wstrb   = 4'h0;  wvalid = 1'b0;
        bready  = 1'b0;
        araddr  = 4'h0;   arvalid = 1'b0;
        rready  = 1'b0;
        tdata   = 512'd0; tvalid  = 1'b0;  tlast  = 1'b0;
        got_start = 1'b0;

        // synchronous reset for 4 cycles
        repeat (4) @(posedge clk);
        #0.1; rst_n = 1'b1;

        $display("=== tb_interface ===");

        // ════════════════════════════════════════════════════════════════
        // TEST 1 — AXI4-Lite write: TILE_LEN = 9 to address 0x08
        //   Full handshake: AW channel → W channel → B response
        // ════════════════════════════════════════════════════════════════
        axil_write(4'h8, 32'h00000009);

        // bresp is a constant OKAY (2'b00); bvalid was seen inside the task
        if (bresp === 2'b00) begin
            $display("  T1 [AXI4-Lite write TILE_LEN=9] : PASS  bresp=2'b00 (OKAY)");
            pass_count = pass_count + 1;
        end else begin
            $display("  T1 [AXI4-Lite write TILE_LEN=9] : FAIL  bresp=0x%01h", bresp);
            fail_count = fail_count + 1;
        end

        // ════════════════════════════════════════════════════════════════
        // TEST 2 — AXI4-Lite read: read TILE_LEN back from address 0x08
        //   Verifies internal register holds what was written in T1
        // ════════════════════════════════════════════════════════════════
        axil_read(4'h8, read_val);

        if (read_val[7:0] === 8'd9 && rresp === 2'b00) begin
            $display("  T2 [AXI4-Lite read  TILE_LEN]  : PASS  rdata=0x%08h  rresp=OKAY", read_val);
            pass_count = pass_count + 1;
        end else begin
            $display("  T2 [AXI4-Lite read  TILE_LEN]  : FAIL  rdata=0x%08h  rresp=0x%01h", read_val, rresp);
            fail_count = fail_count + 1;
        end

        // ════════════════════════════════════════════════════════════════
        // TEST 3 — AXI4-Stream beat
        //   TREADY must be high whenever TVALID is asserted (always-ready).
        //   Transfer is considered complete when TVALID & TREADY are both 1.
        // ════════════════════════════════════════════════════════════════
        @(posedge clk); #0.1;
        tdata  = {{480{1'b0}}, 32'hDEAD_BEEF};  // non-trivial 512-bit pattern
        tvalid = 1'b1;
        tlast  = 1'b1;

        if (tready === 1'b1) begin
            $display("  T3 [AXI4-Stream beat]           : PASS  tready=1 (beat accepted)");
            pass_count = pass_count + 1;
        end else begin
            $display("  T3 [AXI4-Stream beat]           : FAIL  tready=0");
            fail_count = fail_count + 1;
        end

        @(posedge clk); #0.1;
        tvalid = 1'b0;  tlast = 1'b0;

        // ════════════════════════════════════════════════════════════════
        // TEST 4 — CTRL start pulse
        //   Write 0x1 to CTRL (0x00); DUT must assert core_start for one cycle.
        //   Sample core_start at 0.1 ns after the handshake posedge.
        // ════════════════════════════════════════════════════════════════
        @(posedge clk); #0.1;
        awaddr  = 4'h0;  awvalid = 1'b1;
        wdata   = 32'h00000001;  wvalid = 1'b1;  wstrb = 4'hF;

        while (!(awready && wready)) @(posedge clk);
        @(posedge clk); #0.1;           // handshake posedge — reg_start latched
        awvalid  = 1'b0;  wvalid = 1'b0;
        got_start = core_start;         // sample core_start right after posedge

        while (!bvalid) @(posedge clk);
        #0.1; bready = 1'b1;
        @(posedge clk); #0.1;
        bready = 1'b0;

        if (got_start === 1'b1) begin
            $display("  T4 [CTRL start pulse]           : PASS  core_start pulsed high");
            pass_count = pass_count + 1;
        end else begin
            $display("  T4 [CTRL start pulse]           : FAIL  core_start was not high");
            fail_count = fail_count + 1;
        end

        // ── final verdict ─────────────────────────────────────────────────
        $display("---");
        if (fail_count == 0)
            $display("PASS — all %0d tests passed.", pass_count);
        else
            $display("FAIL — %0d of %0d tests failed.", fail_count, pass_count + fail_count);

        $finish;
    end

    // ── watchdog ──────────────────────────────────────────────────────────
    initial begin
        #10000;
        $display("FAIL — simulation timeout (>10000 ns).");
        $finish;
    end

endmodule

project/m2/sim/waveform.vcd
$date
	Fri May 01 21:13:44 2026
$end
$version
	Icarus Verilog
$end
$timescale
	1ps
$end
$scope module tb_interface $end
$var wire 2 ! bresp [1:0] $end
$var wire 1 " core_done $end
$var wire 1 # core_ready $end
$var wire 32 $ core_result [31:0] $end
$var wire 2 % rresp [1:0] $end
$var wire 1 & tready $end
$var wire 1 ' wready $end
$var wire 1 ( rvalid $end
$var wire 32 ) rdata [31:0] $end
$var wire 8 * core_tile_len [7:0] $end
$var wire 1 + core_start $end
$var wire 1 , bvalid $end
$var wire 1 - awready $end
$var wire 1 . arready $end
$var reg 4 / araddr [3:0] $end
$var reg 1 0 arvalid $end
$var reg 4 1 awaddr [3:0] $end
$var reg 1 2 awvalid $end
$var reg 1 3 bready $end
$var reg 1 4 clk $end
$var reg 1 5 got_start $end
$var reg 32 6 read_val [31:0] $end
$var reg 1 7 rready $end
$var reg 1 8 rst_n $end
$var reg 512 9 tdata [511:0] $end
$var reg 1 : tlast $end
$var reg 1 ; tvalid $end
$var reg 32 < wdata [31:0] $end
$var reg 4 = wstrb [3:0] $end
$var reg 1 > wvalid $end
$var integer 32 ? fail_count [31:0] $end
$var integer 32 @ pass_count [31:0] $end
$upscope $end
$enddefinitions $end
#0
$dumpvars
b0 @
b0 ?
0>
b0 =
b0 <
0;
0:
b0 9
08
07
bx 6
05
04
03
02
b0 1
00
b0 /
x.
x-
x,
x+
bx *
bx )
x(
x'
1&
b0 %
b0 $
1#
0"
b0 !
$end
#500
1'
1-
b0 *
0+
b0 )
1.
0(
0,
14
#1000
04
#1500
14
#2000
04
#2500
14
#3000
04
#3500
14
#3600
18
#4000
04
#4500
14
#4600
b1111 =
1>
b1001 <
12
b1000 1
#5000
04
#5500
0'
0-
1,
b1001 *
14
#5600
0>
02
#5700
13
#6000
04
#6500
1-
1'
0,
14
#6600
b1 @
03
#7000
04
#7500
14
#7600
10
b1000 /
#8000
04
#8500
b1001 )
0.
1(
14
#8600
00
#8700
17
#9000
04
#9500
1.
0(
14
#9600
b10 @
b1001 6
07
#10000
04
#10500
14
#10600
b11 @
1:
1;
b11011110101011011011111011101111 9
#11000
04
#11500
14
#11600
0:
0;
#12000
04
#12500
14
#12600
1>
b1 <
12
b0 1
#13000
04
#13500
0'
0-
1,
1+
14
#13600
15
0>
02
#13700
13
#14000
04
#14500
1-
1'
0,
0+
14
#14600
b100 @
03
