codefest/cf04/cocotb_mac/mac_correct.sv
//LLM used - Claude 4.7 Opus
/* Prompt - I'm designing a AI accelerator chiplet for which i have to build a building block "INT8 MAC unit". Can you generate this block in SystemVerilog 
Specifications :
Module name: mac
Inputs: clk (1-bit), rst (1-bit, active-high synchronous reset), a (8-bit signed), b (8-bit
signed)
Output: out (32-bit signed accumulator)
Behavior: On each rising clock edge: if rst is high, set out to 0; else add a×b to out.
Constraints: Synthesizable SystemVerilog only. No initial blocks, no $display, no delays
(#). Use always_ff.
*/
module mac (
    input  logic        clk,
    input  logic        rst,
    input  logic [7:0]  a,
    input  logic [7:0]  b,
    output logic [31:0] out
);

    always_ff @(posedge clk) begin
        if (rst)
            out <= 32'sd0;
        else
            out <= $signed(out) + ($signed(a) * $signed(b));
    end

endmodule

codefest/cf04/hdl/mac_tb.sv
// Testbench for mac_llm_B.sv (INT8 MAC unit)
// Stimulus: [a=3,b=4] x3 cycles → assert rst → [a=-5,b=2] x2 cycles
// Compatible with VCS and Questasim; produces VCD + transcript

`timescale 1ns/1ps

module mac_tb;

    // ------------------------------------------------------------------ //
    //  DUT signals
    // ------------------------------------------------------------------ //
    logic              clk;
    logic              rst;
    logic signed [7:0] a;
    logic signed [7:0] b;
    logic signed [31:0] out;

    // ------------------------------------------------------------------ //
    //  DUT instantiation
    // ------------------------------------------------------------------ //
    mac dut (
        .clk (clk),
        .rst (rst),
        .a   (a),
        .b   (b),
        .out (out)
    );

    // ------------------------------------------------------------------ //
    //  Clock: 10 ns period (100 MHz)
    // ------------------------------------------------------------------ //
    initial clk = 1'b0;
    always  #5 clk = ~clk;

    // ------------------------------------------------------------------ //
    //  VCD dump (works on both VCS and Questasim)
    // ------------------------------------------------------------------ //
    initial begin
        $dumpfile("mac_tb.vcd");
        $dumpvars(0, mac_tb);
    end

    // ------------------------------------------------------------------ //
    //  Stimulus + checking
    // ------------------------------------------------------------------ //
    integer cycle_num;
    logic signed [31:0] expected;

    // Helper task: advance one clock, sample outputs 1 ns after posedge
    // (samples after NBA region so always_ff results are stable)
    task automatic tick(
        input integer     exp_val,
        input string      label
    );
        @(posedge clk); #1;
        $display("CYCLE %0d | %-22s | rst=%b a=%4d b=%4d | out=%0d  (expected %0d) | %s",
                 cycle_num, label, rst, $signed(a), $signed(b),
                 $signed(out), exp_val,
                 ($signed(out) === exp_val) ? "PASS" : "*** FAIL ***");
        if ($signed(out) !== exp_val)
            $error("Mismatch at cycle %0d: got %0d, expected %0d", cycle_num, $signed(out), exp_val);
        cycle_num++;
    endtask

    initial begin
        $display("============================================================");
        $display(" mac_tb: INT8 MAC unit simulation");
        $display(" DUT file: mac_llm_B.sv");
        $display("============================================================");
        $display("%-7s | %-22s | %-19s | %-6s | %-16s | %s",
                 "CYCLE", "PHASE", "INPUTS", "out", "expected", "STATUS");
        $display("------------------------------------------------------------");

        // ----- initialise ------------------------------------------------
        cycle_num = 0;
        rst = 1'b1;
        a   = 8'sd0;
        b   = 8'sd0;

        // ----- Cycle 0: initial synchronous reset ------------------------
        // out must become 0
        expected = 32'sd0;
        tick(expected, "RESET (init)");

        // ----- Cycles 1-3: a=3, b=4 -------------------------------------
        // After each posedge: out += 3*4 = 12
        rst = 1'b0;
        a   = 8'sd3;
        b   = 8'sd4;

        // Cycle 1: 0 + 12 = 12
        expected = 32'sd12;
        tick(expected, "a=3 b=4 (cyc 1/3)");

        // Cycle 2: 12 + 12 = 24
        expected = 32'sd24;
        tick(expected, "a=3 b=4 (cyc 2/3)");

        // Cycle 3: 24 + 12 = 36
        expected = 32'sd36;
        tick(expected, "a=3 b=4 (cyc 3/3)");

        // ----- Assert rst (synchronous reset mid-stream) -----------------
        // out must snap to 0 on this rising edge
        rst = 1'b1;
        // a,b intentionally left at 3,4 to confirm rst wins
        expected = 32'sd0;
        tick(expected, "RESET (mid-stream)");

        // ----- Cycles 5-6: a=-5, b=2 ------------------------------------
        // After each posedge: out += (-5)*2 = -10
        rst = 1'b0;
        a   = -8'sd5;   // 8'hFB in 2's complement
        b   =  8'sd2;

        // Cycle 5: 0 + (-10) = -10
        expected = -32'sd10;
        tick(expected, "a=-5 b=2 (cyc 1/2)");

        // Cycle 6: -10 + (-10) = -20
        expected = -32'sd20;
        tick(expected, "a=-5 b=2 (cyc 2/2)");

        // ----- Done ------------------------------------------------------
        $display("============================================================");
        $display(" Simulation complete — %0d cycles exercised", cycle_num);
        $display("============================================================");
        $finish;
    end

endmodule

codefest/cf04/cocotb_mac/mac_tb.vcd
$date
	Sun Apr 26 09:49:34 2026
$end
$version
	Icarus Verilog
$end
$timescale
	1ps
$end
$scope module mac_tb $end
$var wire 32 ! out [31:0] $end
$var reg 8 " a [7:0] $end
$var reg 8 # b [7:0] $end
$var reg 1 $ clk $end
$var reg 32 % expected [31:0] $end
$var reg 1 & rst $end
$var integer 32 ' cycle_num [31:0] $end
$scope module dut $end
$var wire 8 ( a [7:0] $end
$var wire 8 ) b [7:0] $end
$var wire 1 $ clk $end
$var wire 1 & rst $end
$var reg 32 * out [31:0] $end
$upscope $end
$scope task tick $end
$upscope $end
$upscope $end
$enddefinitions $end
#0
$dumpvars
bx *
b0 )
b0 (
b0 '
1&
b0 %
0$
b0 #
b0 "
bx !
$end
#5000
b0 !
b0 *
1$
#6000
b1100 %
b100 #
b100 )
b11 "
b11 (
0&
b1 '
#10000
0$
#15000
b1100 !
b1100 *
1$
#16000
b11000 %
b10 '
#20000
0$
#25000
b11000 !
b11000 *
1$
#26000
b100100 %
b11 '
#30000
0$
#35000
b100100 !
b100100 *
1$
#36000
b0 %
1&
b100 '
#40000
0$
#45000
b0 !
b0 *
1$
#46000
b11111111111111111111111111110110 %
b10 #
b10 )
b11111011 "
b11111011 (
0&
b101 '
#50000
0$
#55000
b11111111111111111111111111110110 !
b11111111111111111111111111110110 *
1$
#56000
b11111111111111111111111111101100 %
b110 '
#60000
0$
#65000
b11111111111111111111111111101100 !
b11111111111111111111111111101100 *
1$
#66000
b111 '
